cmake_analyzer/__init__.py
cmake_analyzer/__main__.py
cmake_analyzer/analyzer.py
cmake_analyzer/core/__init__.py
cmake_analyzer/core/module_base.py
cmake_analyzer/core/modules_loader.py
cmake_analyzer/core/parser.py
cmake_analyzer/core/reporter_base.py
cmake_analyzer/core/traverser.py
cmake_analyzer/modules/bugprone_version_usage.py
cmake_analyzer/modules/deprecated_commands.py
cmake_analyzer/modules/deprecated_link_prefix.py
cmake_analyzer/modules/deprecated_qt5_use_modules.py
cmake_analyzer/modules/style_add_definitions.py
cmake_analyzer/modules/style_use_access_modifiers.py
cmake_analyzer/reporters/__init__.py
cmake_analyzer/reporters/simple.py
cmake_analyzer/static/simple_grammar.ebnf
cmake_analyzer-0.1.dist-info/LICENSE.md
cmake_analyzer-0.1.dist-info/METADATA
cmake_analyzer-0.1.dist-info/WHEEL
cmake_analyzer-0.1.dist-info/entry_points.txt
cmake_analyzer-0.1.dist-info/top_level.txt
cmake_analyzer-0.1.dist-info/zip-safe
cmake_analyzer-0.1.dist-info/RECORD
