Metadata-Version: 2.1
Name: cmake-analyzer
Version: 0.1
Summary: CMake Analyzer (cmana) is a tool that helps developers to find common issues in CMake code. It searches for deprecated commands/keywords, bad codestyle, potential problems.
Home-page: https://bitbucket.org/ArchiDevil/cmake-analyzer
Author: Denis Bezykornov
Author-email: archidevil52@gmail.com
License: MIT
Project-URL: Homepage, https://bitbucket.org/ArchiDevil/cmake-analyzer
Project-URL: Bug Tracker, https://bitbucket.org/ArchiDevil/cmake-analyzer/issues
Project-URL: Source Code, https://bitbucket.org/ArchiDevil/cmake-analyzer/src
Keywords: cmake lint analyzer
Platform: UNKNOWN
Classifier: Topic :: Software Development :: Build Tools
Classifier: Development Status :: 2 - Pre-Alpha
Classifier: Programming Language :: Python :: 3 :: Only
Classifier: Programming Language :: Python :: 3.5
Classifier: Programming Language :: Python :: 3.6
Classifier: Programming Language :: Python :: 3.7
Classifier: Programming Language :: Python :: 3.8
Classifier: Programming Language :: Python :: Implementation :: CPython
Classifier: Environment :: Console
Classifier: Operating System :: OS Independent
Classifier: Intended Audience :: Developers
Classifier: License :: OSI Approved :: MIT License
Requires-Python: >=3.5
Requires-Dist: TatSu (==4.4.0)
